{
   "title": "Total United States vehicles entering in Canada 2018",
   "xAxis": "Month",
   "yAxis": "Number",
   "columnType": "two",
   "graphType": "line",
   "summaryType": "nlp",
   "summary": [
      "The graph shows the trend of the Total Number of United States States vehicles to Canada during the year 2018 . ",
      "The Number drops between January and February shows the minimum value in February . ",
      "From February on it increases and shows the maximum value in August ."
   ],
   "trends": [
      {},
      {
         "4": "0",
         "6": "1",
         "13": "1"
      },
      {
         "1": "1",
         "11": "7"
      }
   ],
   "data": [
      {
         "Month": "January",
         "Number": "572090.0"
      },
      {
         "Month": "February",
         "Number": "573762.0"
      },
      {
         "Month": "March",
         "Number": "689492.0"
      },
      {
         "Month": "April",
         "Number": "663490.0"
      },
      {
         "Month": "May",
         "Number": "836273.0"
      },
      {
         "Month": "June",
         "Number": "1041015.0"
      },
      {
         "Month": "July",
         "Number": "1186277.0"
      },
      {
         "Month": "August",
         "Number": "1193966.0"
      },
      {
         "Month": "September",
         "Number": "893928.0"
      },
      {
         "Month": "October",
         "Number": "782609.0"
      },
      {
         "Month": "November",
         "Number": "665440.0"
      },
      {
         "Month": "December",
         "Number": "713163.0"
      }
   ],
   "gold": "The graph indicates the entering vehicles from the united states in canada in the year of 2018 . It is noticeable that the number is rising sharply by the middle of the year , reaching a maximum of 1200000 in August . Then the value is strong again until the end of the year .\n"
}