{
   "title": "Production of Unprocessed milk in Canada 2017",
   "xAxis": "Month",
   "yAxis": "Farm product price index (FPPI)",
   "columnType": "two",
   "graphType": "line",
   "summaryType": "nlp",
   "summary": [
      "The graph shows the Production of Unprocessed milk in Canada for the year fo 2017 . ",
      "The graph shows Production steadily rising till October and then declines in the months after . ",
      "It is important to note that Production at the end of the year in December is much higher than it was beginning the year in January ."
   ],
   "trends": [
      {},
      {
         "7": "9"
      },
      {
         "14": "11",
         "25": "0"
      }
   ],
   "data": [
      {
         "Month": "January",
         "Farm product price index (FPPI)": "1073.0"
      },
      {
         "Month": "February",
         "Farm product price index (FPPI)": "1095.0"
      },
      {
         "Month": "March",
         "Farm product price index (FPPI)": "1078.0"
      },
      {
         "Month": "April",
         "Farm product price index (FPPI)": "1057.0"
      },
      {
         "Month": "May",
         "Farm product price index (FPPI)": "1060.0"
      },
      {
         "Month": "June",
         "Farm product price index (FPPI)": "1052.0"
      },
      {
         "Month": "July",
         "Farm product price index (FPPI)": "1044.0"
      },
      {
         "Month": "August",
         "Farm product price index (FPPI)": "1055.0"
      },
      {
         "Month": "September",
         "Farm product price index (FPPI)": "1063.0"
      },
      {
         "Month": "October",
         "Farm product price index (FPPI)": "1091.0"
      },
      {
         "Month": "November",
         "Farm product price index (FPPI)": "1080.0"
      },
      {
         "Month": "December",
         "Farm product price index (FPPI)": "1058.0"
      }
   ],
   "gold": "Graph that describes the production of unprocessed milk in Canada in 2017 . The production in October and February is the highest , while there is a significant drop the following two months of each . The production slightly rises in May but it then plunges until July , where the lowest value can be seen .\n"
}